user_activities/__init__.py
user_activities/admin.py
user_activities/apps.py
user_activities/choices.py
user_activities/fields.py
user_activities/filters.py
user_activities/managers.py
user_activities/models.py
user_activities/serializers.py
user_activities/urls.py
user_activities/views.py
user_activities/viewsets.py
user_activities/migrations/0001_initial.py
user_activities/migrations/0002_auto_20181023_1337.py
user_activities/migrations/0003_auto_20181210_1039.py
user_activities/migrations/0004_auto_20191121_1151.py
user_activities/migrations/0005_auto_20200123_1507.py
user_activities/migrations/__init__.py
django_user_activities-1.2.0.dist-info/AUTHORS.rst
django_user_activities-1.2.0.dist-info/LICENSE
django_user_activities-1.2.0.dist-info/METADATA
django_user_activities-1.2.0.dist-info/WHEEL
django_user_activities-1.2.0.dist-info/top_level.txt
django_user_activities-1.2.0.dist-info/RECORD
